directorySearchCogna/__init__.py
directorySearchCogna/directorySearch.py
directorySearchCogna-0.1.0.dist-info/METADATA
directorySearchCogna-0.1.0.dist-info/WHEEL
directorySearchCogna-0.1.0.dist-info/top_level.txt
directorySearchCogna-0.1.0.dist-info/RECORD
